<?xml version = '1.0' encoding = 'UTF-8'?>
<Relation class="oracle.dbtools.crest.model.design.logical.Relation" name="Relation_26" directorySegmentName="seg_0" id="42612FF8-44B8-E42E-DB8A-CD022EE7483A">
<createdBy>Mateusz</createdBy>
<createdTime>2022-12-05 21:27:34 UTC</createdTime>
<ownerDesignName>schemat_ERD</ownerDesignName>
<engineerTo>
<item key="F77F99E3-3927-317A-0967-746CE7840648" value="true"/>
</engineerTo>
<targetTransferable>false</targetTransferable>
<sourcePk>8C7B9A38-6DD4-7DA8-B1ED-B4E4CDD6D4F1</sourcePk>
<identifying>true</identifying>
<optionalSource>true</optionalSource>
<optionalTarget>false</optionalTarget>
<sourceCardinality>1</sourceCardinality>
<sourceEntity>C7378074-CD39-B52C-D4F7-88665AE1B4E3</sourceEntity>
<targetCardinalityString>*</targetCardinalityString>
<targetEntity>578AD7BC-3E15-78B5-297E-BE220DDEECB9</targetEntity>
<transferable>true</transferable>
<deleteRule>NO ACTION</deleteRule>
</Relation>